Workbook

Sheet Data
A1: Invoice Num | B1: Vendor | C1: Company | D1: Month | E1: Invoice Date | F1: Due Date | G1: Payment Date | H1: Status | I1: Invoice Amt USD | J1: Outstanding USD | K1: Days to Pay | L1: Aging Bucket | M1: Days Past Due | N1: Late Payment | O1: Disc Captured | P1: Disc Missed | Q1: Blocked 30d | R1: In Review 15d | S1: Issue Type | T1: Urgency
A2: INV-1001 | B2: Office Supply Co | C2: US01 | D2: Jan-25 | E2: 2025-01-02 | F2: 2025-02-02 | G2: 2025-02-04 | H2: Paid | I2: 525.67 | J2: 0 | K2: 32 | L2: Current | N2: =TRUE() -> TRUE | O2: 0 | P2: 0 | Q2: =FALSE() -> FALSE | R2: =FALSE() -> FALSE | S2: Late Payment | T2: Yellow
A3: INV-1002 | B3: Northside Transport | C3: US02 | D3: Jan-25 | E3: 2025-01-02 | F3: 2025-02-02 | G3: 2025-01-29 | H3: Paid | I3: 2623.07 | J3: 0 | K3: 26 | L3: Current | N3: =FALSE() -> FALSE | O3: 0 | P3: 0 | Q3: =FALSE() -> FALSE | R3: =FALSE() -> FALSE
A4: INV-1003 | B4: Continental Freight | C4: US02 | D4: Jan-25 | E4: 2025-01-02 | F4: 2025-02-02 | G4: 2025-01-11 | H4: Partially Paid | I4: 3342.31 | J4: 1336.92 | L4: 90+ Days | M4: 148 | N4: =FALSE() -> FALSE | O4: 0 | P4: 66.85 | Q4: =FALSE() -> FALSE | R4: =FALSE() -> FALSE | S4: Missed Discount | T4: Amber
A5: INV-1004 | B5: Northside Transport | C5: US02 | D5: Jan-25 | E5: 2025-01-03 | F5: 2025-02-05 | G5: 2025-02-07 | H5: Paid | I5: 2363.08 | J5: 0 | K5: 32 | L5: Current | N5: =TRUE() -> TRUE | O5: 0 | P5: 0 | Q5: =FALSE() -> FALSE | R5: =FALSE() -> FALSE | S5: Late Payment | T5: Yellow
A6: INV-1005 | B6: EuroFreight GmbH | C6: US02 | D6: Jan-25 | E6: 2025-01-07 | F6: 2025-02-07 | G6: 2025-01-21 | H6: Paid | I6: 1905.51 | J6: 0 | K6: 13 | L6: Current | N6: =FALSE() -> FALSE | O6: 0 | P6: 0 | Q6: =FALSE() -> FALSE | R6: =FALSE() -> FALSE
A7: INV-1006 | B7: IT Services Group | C7: US01 | D7: Jan-25 | E7: 2025-01-08 | F7: 2025-02-23 | G7: 2025-02-02 | H7: Paid | I7: 1337.83 | J7: 0 | K7: 24 | L7: Current | N7: =FALSE() -> FALSE | O7: 0 | P7: 0 | Q7: =FALSE() -> FALSE | R7: =FALSE() -> FALSE
A8: INV-1007 | B8: Logistics Partners | C8: US02 | D8: Jan-25 | E8: 2025-01-09 | F8: 2025-02-09 | G8: 2025-01-18 | H8: Paid | I8: 1444.45 | J8: 0 | K8: 8 | L8: Current | N8: =FALSE() -> FALSE | O8: 0 | P8: 0 | Q8: =FALSE() -> FALSE | R8: =FALSE() -> FALSE
A9: INV-1008 | B9: Logistics Partners | C9: US02 | D9: Jan-25 | E9: 2025-01-09 | F9: 2025-02-09 | G9: 2025-01-15 | H9: Paid | I9: 2542.85 | J9: 0 | K9: 5 | L9: Current | N9: =FALSE() -> FALSE | O9: 0 | P9: 0 | Q9: =FALSE() -> FALSE | R9: =FALSE() -> FALSE
A10: INV-1009 | B10: West Coast Paper | C10: US01 | D10: Jan-25 | E10: 2025-01-09 | F10: 2025-01-25 | H10: Blocked | I10: 567.87 | J10: 567.87 | L10: 90+ Days | M10: 156 | N10: =FALSE() -> FALSE | O10: 0 | P10: 0 | Q10: =TRUE() -> TRUE | R10: =FALSE() -> FALSE | S10: Blocked Over 30 Days | T10: Red
A11: INV-1010 | B11: Suministros MX | C11: MX01 | D11: Jan-25 | E11: 2025-01-15 | F11: 2025-02-15 | H11: Blocked | I11: 407.86 | J11: 407.86 | L11: 90+ Days | M11: 135 | N11: =FALSE() -> FALSE | O11: 0 | P11: 0 | Q11: =TRUE() -> TRUE | R11: =FALSE() -> FALSE | S11: Blocked Over 30 Days | T11: Red
A12: INV-1011 | B12: West Coast Paper | C12: US01 | D12: Jan-25 | E12: 2025-01-16 | F12: 2025-02-01 | G12: 2025-01-30 | H12: Paid | I12: 410.58 | J12: 0 | K12: 13 | L12: Current | N12: =FALSE() -> FALSE | O12: 0 | P12: 0 | Q12: =FALSE() -> FALSE | R12: =FALSE() -> FALSE
A13: INV-1012 | B13: Vendor One Foods | C13: US01 | D13: Jan-25 | E13: 2025-01-18 | F13: 2025-02-19 | G13: 2025-02-10 | H13: Paid | I13: 1478.39 | J13: 0 | K13: 21 | L13: Current | N13: =FALSE() -> FALSE | O13: 0 | P13: 0 | Q13: =FALSE() -> FALSE | R13: =FALSE() -> FALSE
A14: INV-1013 | B14: Cleaning Solutions | C14: US02 | D14: Jan-25 | E14: 2025-01-19 | F14: 2025-02-19 | G14: 2025-02-16 | H14: Paid | I14: 379.47 | J14: 0 | K14: 27 | L14: Current | N14: =FALSE() -> FALSE | O14: 0 | P14: 0 | Q14: =FALSE() -> FALSE | R14: =FALSE() -> FALSE
A15: INV-1014 | B15: City Utilities | C15: US01 | D15: Jan-25 | E15: 2025-01-20 | F15: 2025-02-05 | H15: Blocked | I15: 651.71 | J15: 651.71 | L15: 90+ Days | M15: 145 | N15: =FALSE() -> FALSE | O15: 0 | P15: 0 | Q15: =TRUE() -> TRUE | R15: =FALSE() -> FALSE | S15: Blocked Over 30 Days | T15: Red
A16: INV-1015 | B16: Fresh Beverages Inc | C16: US01 | D16: Jan-25 | E16: 2025-01-23 | F16: 2025-02-23 | G16: 2025-02-05 | H16: Paid | I16: 2604.2 | J16: 0 | K16: 12 | L16: Current | N16: =FALSE() -> FALSE | O16: 0 | P16: 0 | Q16: =FALSE() -> FALSE | R16: =FALSE() -> FALSE
A17: INV-1016 | B17: Metro Packaging | C17: US02 | D17: Jan-25 | E17: 2025-01-24 | F17: 2025-02-26 | G17: 2025-02-05 | H17: Paid | I17: 962.83 | J17: 0 | K17: 9 | L17: Current | N17: =FALSE() -> FALSE | O17: 19.26 | P17: 0 | Q17: =FALSE() -> FALSE | R17: =FALSE() -> FALSE
A18: INV-1017 | B18: Alpha Facilities Mgmt | C18: US03 | D18: Jan-25 | E18: 2025-01-24 | F18: 2025-02-26 | G18: 2025-02-04 | H18: Paid | I18: 700.72 | J18: 0 | K18: 8 | L18: Current | N18: =FALSE() -> FALSE | O18: 0 | P18: 0 | Q18: =FALSE() -> FALSE | R18: =FALSE() -> FALSE
A19: INV-1018 | B19: Packaging World | C19: US02 | D19: Jan-25 | E19: 2025-01-25 | F19: 2025-02-26 | H19: In Review | I19: 482.87 | J19: 482.87 | L19: 90+ Days | M19: 124 | N19: =FALSE() -> FALSE | O19: 0 | P19: 0 | Q19: =FALSE() -> FALSE | R19: =TRUE() -> TRUE | S19: In Review Over 15 Days | T19: Amber
A20: INV-1019 | B20: Continental Freight | C20: US02 | D20: Jan-25 | E20: 2025-01-26 | F20: 2025-02-26 | G20: 2025-02-22 | H20: Paid | I20: 3170.94 | J20: 0 | K20: 26 | L20: Current | N20: =FALSE() -> FALSE | O20: 0 | P20: 63.42 | Q20: =FALSE() -> FALSE | R20: =FALSE() -> FALSE | S20: Missed Discount | T20: Amber
A21: INV-1020 | B21: West Coast Paper | C21: US01 | D21: Feb-25 | E21: 2025-02-03 | F21: 2025-02-19 | G21: 2025-02-14 | H21: Paid | I21: 471.21 | J21: 0 | K21: 10 | L21: Current | N21: =FALSE() -> FALSE | O21: 0 | P21: 0 | Q21: =FALSE() -> FALSE | R21: =FALSE() -> FALSE
A22: INV-1021 | B22: Packaging World | C22: US02 | D22: Feb-25 | E22: 2025-02-04 | F22: 2025-03-07 | H22: Voided | I22: 0 | J22: 0 | L22: Current | N22: =FALSE() -> FALSE | O22: 0 | P22: 0 | Q22: =FALSE() -> FALSE | R22: =FALSE() -> FALSE | S22: Voided Invoice | T22: Yellow
A23: INV-1022 | B23: Vendor One Foods | C23: US01 | D23: Feb-25 | E23: 2025-02-04 | F23: 2025-03-07 | G23: 2025-02-14 | H23: Paid | I23: 3926.93 | J23: 0 | K23: 9 | L23: Current | N23: =FALSE() -> FALSE | O23: 0 | P23: 0 | Q23: =FALSE() -> FALSE | R23: =FALSE() -> FALSE
A24: INV-1023 | B24: Alpha Facilities Mgmt | C24: US03 | D24: Feb-25 | E24: 2025-02-04 | F24: 2025-03-07 | H24: Overdue | I24: 811.75 | J24: 811.75 | L24: 90+ Days | M24: 115 | N24: =FALSE() -> FALSE | O24: 0 | P24: 0 | Q24: =FALSE() -> FALSE | R24: =FALSE() -> FALSE | S24: Overdue Invoice | T24: Red
A25: INV-1024 | B25: Packaging World | C25: US02 | D25: Feb-25 | E25: 2025-02-05 | F25: 2025-03-08 | G25: 2025-03-06 | H25: Paid | I25: 804.33 | J25: 0 | K25: 28 | L25: Current | N25: =FALSE() -> FALSE | O25: 0 | P25: 0 | Q25: =FALSE() -> FALSE | R25: =FALSE() -> FALSE
A26: INV-1025 | B26: Fresh Beverages Inc | C26: US01 | D26: Feb-25 | E26: 2025-02-05 | F26: 2025-03-08 | G26: 2025-02-27 | H26: Paid | I26: 1550.73 | J26: 0 | K26: 21 | L26: Current | N26: =FALSE() -> FALSE | O26: 0 | P26: 0 | Q26: =FALSE() -> FALSE | R26: =FALSE() -> FALSE
A27: INV-1026 | B27: IT Services Group | C27: US01 | D27: Feb-25 | E27: 2025-02-05 | F27: 2025-03-23 | G27: 2025-03-14 | H27: Paid | I27: 874.95 | J27: 0 | K27: 36 | L27: Current | N27: =FALSE() -> FALSE | O27: 0 | P27: 0 | Q27: =FALSE() -> FALSE | R27: =FALSE() -> FALSE
A28: INV-1027 | B28: Office Supply Co | C28: US01 | D28: Feb-25 | E28: 2025-02-06 | F28: 2025-03-09 | H28: Overdue | I28: 418.56 | J28: 418.56 | L28: 90+ Days | M28: 113 | N28: =FALSE() -> FALSE | O28: 0 | P28: 0 | Q28: =FALSE() -> FALSE | R28: =FALSE() -> FALSE | S28: Overdue Invoice | T28: Red
A29: INV-1028 | B29: Metro Packaging | C29: US02 | D29: Feb-25 | E29: 2025-02-08 | F29: 2025-03-12 | G29: 2025-02-22 | H29: Paid | I29: 609.56 | J29: 0 | K29: 12 | L29: Current | N29: =FALSE() -> FALSE | O29: 0 | P29: 12.19 | Q29: =FALSE() -> FALSE | R29: =FALSE() -> FALSE | S29: Missed Discount | T29: Amber
A30: INV-1029 | B30: Suministros MX | C30: MX01 | D30: Feb-25 | E30: 2025-02-09 | F30: 2025-03-12 | H30: Voided | I30: 0 | J30: 0 | L30: Current | N30: =FALSE() -> FALSE | O30: 0 | P30: 0 | Q30: =FALSE() -> FALSE | R30: =FALSE() -> FALSE | S30: Voided Invoice | T30: Yellow
A31: INV-1030 | B31: Office Supply Co | C31: US01 | D31: Feb-25 | E31: 2025-02-10 | F31: 2025-03-13 | G31: 2025-03-25 | H31: Paid | I31: 380.45 | J31: 0 | K31: 42 | L31: Current | N31: =TRUE() -> TRUE | O31: 0 | P31: 0 | Q31: =FALSE() -> FALSE | R31: =FALSE() -> FALSE | S31: Late Payment | T31: Yellow
A32: INV-1031 | B32: City Utilities | C32: US01 | D32: Feb-25 | E32: 2025-02-10 | F32: 2025-02-26 | H32: Overdue | I32: 661.57 | J32: 661.57 | L32: 90+ Days | M32: 124 | N32: =FALSE() -> FALSE | O32: 0 | P32: 0 | Q32: =FALSE() -> FALSE | R32: =FALSE() -> FALSE | S32: Overdue Invoice | T32: Red
A33: INV-1032 | B33: EuroFreight GmbH | C33: US02 | D33: Feb-25 | E33: 2025-02-11 | F33: 2025-03-14 | H33: Overdue | I33: 2242.02 | J33: 2242.02 | L33: 90+ Days | M33: 108 | N33: =FALSE() -> FALSE | O33: 0 | P33: 0 | Q33: =FALSE() -> FALSE | R33: =FALSE() -> FALSE | S33: Overdue Invoice | T33: Red
A34: INV-1033 | B34: Fresh Beverages Inc | C34: US01 | D34: Feb-25 | E34: 2025-02-13 | F34: 2025-03-16 | G34: 2025-03-11 | H34: Paid | I34: 4371.46 | J34: 0 | K34: 25 | L34: Current | N34: =FALSE() -> FALSE | O34: 0 | P34: 0 | Q34: =FALSE() -> FALSE | R34: =FALSE() -> FALSE
A35: INV-1034 | B35: IT Services Group | C35: US01 | D35: Feb-25 | E35: 2025-02-19 | F35: 2025-04-06 | H35: Overdue | I35: 1530.64 | J35: 1530.64 | L35: 61-90 Days | M35: 85 | N35: =FALSE() -> FALSE | O35: 0 | P35: 0 | Q35: =FALSE() -> FALSE | R35: =FALSE() -> FALSE | S35: Overdue Invoice | T35: Red
A36: INV-1035 | B36: Vendor One Foods | C36: US01 | D36: Feb-25 | E36: 2025-02-19 | F36: 2025-03-22 | H36: Overdue | I36: 1358.95 | J36: 1358.95 | L36: 90+ Days | M36: 100 | N36: =FALSE() -> FALSE | O36: 0 | P36: 0 | Q36: =FALSE() -> FALSE | R36: =FALSE() -> FALSE | S36: Overdue Invoice | T36: Red
A37: INV-1036 | B37: Metro Packaging | C37: US02 | D37: Feb-25 | E37: 2025-02-20 | F37: 2025-03-23 | H37: Overdue | I37: 691.72 | J37: 691.72 | L37: 90+ Days | M37: 99 | N37: =FALSE() -> FALSE | O37: 0 | P37: 13.83 | Q37: =FALSE() -> FALSE | R37: =FALSE() -> FALSE | S37: Missed Discount | T37: Amber
A38: INV-1037 | B38: City Utilities | C38: US01 | D38: Feb-25 | E38: 2025-02-21 | F38: 2025-03-11 | G38: 2025-03-10 | H38: Paid | I38: 673.24 | J38: 0 | K38: 14 | L38: Current | N38: =FALSE() -> FALSE | O38: 0 | P38: 0 | Q38: =FALSE() -> FALSE | R38: =FALSE() -> FALSE
A39: INV-1038 | B39: Cleaning Solutions | C39: US02 | D39: Feb-25 | E39: 2025-02-21 | F39: 2025-03-26 | H39: Voided | I39: 0 | J39: 0 | L39: Current | N39: =FALSE() -> FALSE | O39: 0 | P39: 0 | Q39: =FALSE() -> FALSE | R39: =FALSE() -> FALSE | S39: Voided Invoice | T39: Yellow
A40: INV-1039 | B40: Cleaning Solutions | C40: US02 | D40: Feb-25 | E40: 2025-02-22 | F40: 2025-03-26 | G40: 2025-03-22 | H40: Paid | I40: 426.05 | J40: 0 | K40: 26 | L40: Current | N40: =FALSE() -> FALSE | O40: 0 | P40: 0 | Q40: =FALSE() -> FALSE | R40: =FALSE() -> FALSE
A41: INV-1040 | B41: Northside Transport | C41: US02 | D41: Feb-25 | E41: 2025-02-25 | F41: 2025-03-28 | H41: Overdue | I41: 1754.93 | J41: 1754.93 | L41: 90+ Days | M41: 94 | N41: =FALSE() -> FALSE | O41: 0 | P41: 0 | Q41: =FALSE() -> FALSE | R41: =FALSE() -> FALSE | S41: Overdue Invoice | T41: Red
A42: INV-1041 | B42: Logistics Partners | C42: US02 | D42: Feb-25 | E42: 2025-02-26 | F42: 2025-03-29 | G42: 2025-03-09 | H42: Paid | I42: 2311.69 | J42: 0 | K42: 10 | L42: Current | N42: =FALSE() -> FALSE | O42: 0 | P42: 0 | Q42: =FALSE() -> FALSE | R42: =FALSE() -> FALSE
A43: INV-1042 | B43: Continental Freight | C43: US02 | D43: Feb-25 | E43: 2025-02-26 | F43: 2025-03-29 | G43: 2025-03-21 | H43: Paid | I43: 2823.59 | J43: 0 | K43: 22 | L43: Current | N43: =FALSE() -> FALSE | O43: 0 | P43: 56.47 | Q43: =FALSE() -> FALSE | R43: =FALSE() -> FALSE | S43: Missed Discount | T43: Amber
A44: INV-1043 | B44: EuroFreight GmbH | C44: US02 | D44: Mar-25 | E44: 2025-03-03 | F44: 2025-04-03 | G44: 2025-03-28 | H44: Paid | I44: 3091.59 | J44: 0 | K44: 24 | L44: Current | N44: =FALSE() -> FALSE | O44: 0 | P44: 0 | Q44: =FALSE() -> FALSE | R44: =FALSE() -> FALSE
A45: INV-1044 | B45: Packaging World | C45: US02 | D45: Mar-25 | E45: 2025-03-07 | F45: 2025-04-09 | G45: 2025-04-21 | H45: Paid | I45: 1105.13 | J45: 0 | K45: 42 | L45: Current | N45: =TRUE() -> TRUE | O45: 0 | P45: 0 | Q45: =FALSE() -> FALSE | R45: =FALSE() -> FALSE | S45: Late Payment | T45: Yellow
A46: INV-1045 | B46: Vendor One Foods | C46: US01 | D46: Mar-25 | E46: 2025-03-07 | F46: 2025-04-09 | G46: 2025-03-26 | H46: Paid | I46: 4713.05 | J46: 0 | K46: 16 | L46: Current | N46: =FALSE() -> FALSE | O46: 0 | P46: 0 | Q46: =FALSE() -> FALSE | R46: =FALSE() -> FALSE
A47: INV-1046 | B47: Fresh Beverages Inc | C47: US01 | D47: Mar-25 | E47: 2025-03-08 | F47: 2025-04-09 | H47: Overdue | I47: 4248.49 | J47: 4248.49 | L47: 61-90 Days | M47: 82 | N47: =FALSE() -> FALSE | O47: 0 | P47: 0 | Q47: =FALSE() -> FALSE | R47: =FALSE() -> FALSE | S47: Overdue Invoice | T47: Red
A48: INV-1047 | B48: Continental Freight | C48: US02 | D48: Mar-25 | E48: 2025-03-09 | F48: 2025-04-09 | H48: Overdue | I48: 3132.97 | J48: 3132.97 | L48: 61-90 Days | M48: 82 | N48: =FALSE() -> FALSE | O48: 0 | P48: 62.66 | Q48: =FALSE() -> FALSE | R48: =FALSE() -> FALSE | S48: Missed Discount | T48: Amber
A49: INV-1048 | B49: Cleaning Solutions | C49: US02 | D49: Mar-25 | E49: 2025-03-10 | F49: 2025-04-10 | G49: 2025-03-18 | H49: Paid | I49: 786.45 | J49: 0 | K49: 7 | L49: Current | N49: =FALSE() -> FALSE | O49: 0 | P49: 0 | Q49: =FALSE() -> FALSE | R49: =FALSE() -> FALSE
A50: INV-1049 | B50: Alpha Facilities Mgmt | C50: US03 | D50: Mar-25 | E50: 2025-03-12 | F50: 2025-04-12 | G50: 2025-03-27 | H50: Paid | I50: 364.86 | J50: 0 | K50: 14 | L50: Current | N50: =FALSE() -> FALSE | O50: 0 | P50: 0 | Q50: =FALSE() -> FALSE | R50: =FALSE() -> FALSE
A51: INV-1050 | B51: Packaging World | C51: US02 | D51: Mar-25 | E51: 2025-03-13 | F51: 2025-04-13 | H51: Overdue | I51: 577.95 | J51: 577.95 | L51: 61-90 Days | M51: 78 | N51: =FALSE() -> FALSE | O51: 0 | P51: 0 | Q51: =FALSE() -> FALSE | R51: =FALSE() -> FALSE | S51: Overdue Invoice | T51: Red
A52: INV-1051 | B52: Office Supply Co | C52: US01 | D52: Mar-25 | E52: 2025-03-14 | F52: 2025-04-16 | H52: Overdue | I52: 508.29 | J52: 508.29 | L52: 61-90 Days | M52: 75 | N52: =FALSE() -> FALSE | O52: 0 | P52: 0 | Q52: =FALSE() -> FALSE | R52: =FALSE() -> FALSE | S52: Overdue Invoice | T52: Red
A53: INV-1052 | B53: Cleaning Solutions | C53: US02 | D53: Mar-25 | E53: 2025-03-14 | F53: 2025-04-16 | G53: 2025-03-25 | H53: Partially Paid | I53: 576.18 | J53: 288.09 | L53: 61-90 Days | M53: 75 | N53: =FALSE() -> FALSE | O53: 0 | P53: 0 | Q53: =FALSE() -> FALSE | R53: =FALSE() -> FALSE | S53: Overdue Invoice | T53: Red
A54: INV-1053 | B54: Suministros MX | C54: MX01 | D54: Mar-25 | E54: 2025-03-14 | F54: 2025-04-16 | H54: Overdue | I54: 578.92 | J54: 578.92 | L54: 61-90 Days | M54: 75 | N54: =FALSE() -> FALSE | O54: 0 | P54: 0 | Q54: =FALSE() -> FALSE | R54: =FALSE() -> FALSE | S54: Overdue Invoice | T54: Red
A55: INV-1054 | B55: Logistics Partners | C55: US02 | D55: Mar-25 | E55: 2025-03-16 | F55: 2025-04-16 | H55: Blocked | I55: 2582.09 | J55: 2582.09 | L55: 61-90 Days | M55: 75 | N55: =FALSE() -> FALSE | O55: 0 | P55: 0 | Q55: =TRUE() -> TRUE | R55: =FALSE() -> FALSE | S55: Blocked Over 30 Days | T55: Red
A56: INV-1055 | B56: IT Services Group | C56: US01 | D56: Mar-25 | E56: 2025-03-19 | F56: 2025-05-04 | H56: Overdue | I56: 1477.39 | J56: 1477.39 | L56: 31-60 Days | M56: 57 | N56: =FALSE() -> FALSE | O56: 0 | P56: 0 | Q56: =FALSE() -> FALSE | R56: =FALSE() -> FALSE | S56: Overdue Invoice | T56: Red
A57: INV-1056 | B57: Northside Transport | C57: US02 | D57: Mar-25 | E57: 2025-03-21 | F57: 2025-04-23 | G57: 2025-04-28 | H57: Paid | I57: 1552.23 | J57: 0 | K57: 35 | L57: Current | N57: =TRUE() -> TRUE | O57: 0 | P57: 0 | Q57: =FALSE() -> FALSE | R57: =FALSE() -> FALSE | S57: Late Payment | T57: Yellow
A58: INV-1057 | B58: Logistics Partners | C58: US02 | D58: Mar-25 | E58: 2025-03-22 | F58: 2025-04-23 | G58: 2025-04-01 | H58: Paid | I58: 1748.09 | J58: 0 | K58: 8 | L58: Current | N58: =FALSE() -> FALSE | O58: 0 | P58: 0 | Q58: =FALSE() -> FALSE | R58: =FALSE() -> FALSE
A59: INV-1058 | B59: Fresh Beverages Inc | C59: US01 | D59: Mar-25 | E59: 2025-03-23 | F59: 2025-04-23 | H59: Overdue | I59: 4928.37 | J59: 4928.37 | L59: 61-90 Days | M59: 68 | N59: =FALSE() -> FALSE | O59: 0 | P59: 0 | Q59: =FALSE() -> FALSE | R59: =FALSE() -> FALSE | S59: Overdue Invoice | T59: Red
A60: INV-1059 | B60: City Utilities | C60: US01 | D60: Mar-25 | E60: 2025-03-23 | F60: 2025-04-08 | H60: Overdue | I60: 514.49 | J60: 514.49 | L60: 61-90 Days | M60: 83 | N60: =FALSE() -> FALSE | O60: 0 | P60: 0 | Q60: =FALSE() -> FALSE | R60: =FALSE() -> FALSE | S60: Overdue Invoice | T60: Red
A61: INV-1060 | B61: Metro Packaging | C61: US02 | D61: Mar-25 | E61: 2025-03-23 | F61: 2025-04-23 | H61: Overdue | I61: 1151.39 | J61: 1151.39 | L61: 61-90 Days | M61: 68 | N61: =FALSE() -> FALSE | O61: 0 | P61: 23.03 | Q61: =FALSE() -> FALSE | R61: =FALSE() -> FALSE | S61: Missed Discount | T61: Amber
A62: INV-1061 | B62: City Utilities | C62: US01 | D62: Mar-25 | E62: 2025-03-24 | F62: 2025-04-09 | G62: 2025-04-06 | H62: Paid | I62: 346.14 | J62: 0 | K62: 12 | L62: Current | N62: =FALSE() -> FALSE | O62: 0 | P62: 0 | Q62: =FALSE() -> FALSE | R62: =FALSE() -> FALSE
A63: INV-1062 | B63: West Coast Paper | C63: US01 | D63: Mar-25 | E63: 2025-03-26 | F63: 2025-04-11 | H63: Overdue | I63: 390.29 | J63: 390.29 | L63: 61-90 Days | M63: 80 | N63: =FALSE() -> FALSE | O63: 0 | P63: 0 | Q63: =FALSE() -> FALSE | R63: =FALSE() -> FALSE | S63: Overdue Invoice | T63: Red
A64: INV-1063 | B64: West Coast Paper | C64: US01 | D64: Mar-25 | E64: 2025-03-26 | F64: 2025-04-11 | G64: 2025-04-21 | H64: Paid | I64: 591.78 | J64: 0 | K64: 25 | L64: Current | N64: =TRUE() -> TRUE | O64: 0 | P64: 0 | Q64: =FALSE() -> FALSE | R64: =FALSE() -> FALSE | S64: Late Payment | T64: Yellow
A65: INV-1064 | B65: Office Supply Co | C65: US01 | D65: Apr-25 | E65: 2025-04-04 | F65: 2025-05-07 | H65: Overdue | I65: 317.28 | J65: 317.28 | L65: 31-60 Days | M65: 54 | N65: =FALSE() -> FALSE | O65: 0 | P65: 0 | Q65: =FALSE() -> FALSE | R65: =FALSE() -> FALSE | S65: Overdue Invoice | T65: Red
A66: INV-1065 | B66: Cleaning Solutions | C66: US02 | D66: Apr-25 | E66: 2025-04-04 | F66: 2025-05-07 | G66: 2025-04-17 | H66: Paid | I66: 737.13 | J66: 0 | K66: 10 | L66: Current | N66: =FALSE() -> FALSE | O66: 0 | P66: 0 | Q66: =FALSE() -> FALSE | R66: =FALSE() -> FALSE
A67: INV-1066 | B67: Suministros MX | C67: MX01 | D67: Apr-25 | E67: 2025-04-04 | F67: 2025-05-07 | G67: 2025-04-18 | H67: Partially Paid | I67: 1188.58 | J67: 713.15 | L67: 31-60 Days | M67: 54 | N67: =FALSE() -> FALSE | O67: 0 | P67: 0 | Q67: =FALSE() -> FALSE | R67: =FALSE() -> FALSE | S67: Overdue Invoice | T67: Red
A68: INV-1067 | B68: Metro Packaging | C68: US02 | D68: Apr-25 | E68: 2025-04-05 | F68: 2025-05-07 | H68: In Review | I68: 1119.6 | J68: 1119.6 | L68: 31-60 Days | M68: 54 | N68: =FALSE() -> FALSE | O68: 0 | P68: 22.39 | Q68: =FALSE() -> FALSE | R68: =TRUE() -> TRUE | S68: In Review Over 15 Days | T68: Amber
A69: INV-1068 | B69: Fresh Beverages Inc | C69: US01 | D69: Apr-25 | E69: 2025-04-06 | F69: 2025-05-07 | H69: Overdue | I69: 1922.3 | J69: 1922.3 | L69: 31-60 Days | M69: 54 | N69: =FALSE() -> FALSE | O69: 0 | P69: 0 | Q69: =FALSE() -> FALSE | R69: =FALSE() -> FALSE | S69: Overdue Invoice | T69: Red
A70: INV-1069 | B70: Vendor One Foods | C70: US01 | D70: Apr-25 | E70: 2025-04-06 | F70: 2025-05-07 | H70: Overdue | I70: 1368.67 | J70: 1368.67 | L70: 31-60 Days | M70: 54 | N70: =FALSE() -> FALSE | O70: 0 | P70: 0 | Q70: =FALSE() -> FALSE | R70: =FALSE() -> FALSE | S70: Overdue Invoice | T70: Red
A71: INV-1070 | B71: Office Supply Co | C71: US01 | D71: Apr-25 | E71: 2025-04-08 | F71: 2025-05-09 | G71: 2025-04-21 | H71: Paid | I71: 318.03 | J71: 0 | K71: 12 | L71: Current | N71: =FALSE() -> FALSE | O71: 0 | P71: 0 | Q71: =FALSE() -> FALSE | R71: =FALSE() -> FALSE
A72: INV-1071 | B72: Logistics Partners | C72: US02 | D72: Apr-25 | E72: 2025-04-08 | F72: 2025-05-09 | G72: 2025-04-15 | H72: Paid | I72: 2654.51 | J72: 0 | K72: 6 | L72: Current | N72: =FALSE() -> FALSE | O72: 0 | P72: 0 | Q72: =FALSE() -> FALSE | R72: =FALSE() -> FALSE
A73: INV-1072 | B73: City Utilities | C73: US01 | D73: Apr-25 | E73: 2025-04-09 | F73: 2025-04-25 | H73: Overdue | I73: 568.25 | J73: 568.25 | L73: 61-90 Days | M73: 66 | N73: =FALSE() -> FALSE | O73: 0 | P73: 0 | Q73: =FALSE() -> FALSE | R73: =FALSE() -> FALSE | S73: Overdue Invoice | T73: Red
A74: INV-1073 | B74: Vendor One Foods | C74: US01 | D74: Apr-25 | E74: 2025-04-09 | F74: 2025-05-10 | G74: 2025-05-21 | H74: Paid | I74: 2584.04 | J74: 0 | K74: 41 | L74: Current | N74: =TRUE() -> TRUE | O74: 0 | P74: 0 | Q74: =FALSE() -> FALSE | R74: =FALSE() -> FALSE | S74: Late Payment | T74: Yellow
A75: INV-1074 | B75: Fresh Beverages Inc | C75: US01 | D75: Apr-25 | E75: 2025-04-10 | F75: 2025-05-11 | G75: 2025-04-19 | H75: Paid | I75: 4698.93 | J75: 0 | K75: 8 | L75: Current | N75: =FALSE() -> FALSE | O75: 0 | P75: 0 | Q75: =FALSE() -> FALSE | R75: =FALSE() -> FALSE
A76: INV-1075 | B76: Packaging World | C76: US02 | D76: Apr-25 | E76: 2025-04-14 | F76: 2025-05-15 | G76: 2025-05-05 | H76: Paid | I76: 1078.41 | J76: 0 | K76: 20 | L76: Current | N76: =FALSE() -> FALSE | O76: 0 | P76: 0 | Q76: =FALSE() -> FALSE | R76: =FALSE() -> FALSE
A77: INV-1076 | B77: IT Services Group | C77: US01 | D77: Apr-25 | E77: 2025-04-14 | F77: 2025-05-30 | H77: Overdue | I77: 1662.11 | J77: 1662.11 | L77: 31-60 Days | M77: 31 | N77: =FALSE() -> FALSE | O77: 0 | P77: 0 | Q77: =FALSE() -> FALSE | R77: =FALSE() -> FALSE | S77: Overdue Invoice | T77: Red
A78: INV-1077 | B78: EuroFreight GmbH | C78: US02 | D78: Apr-25 | E78: 2025-04-15 | F78: 2025-05-16 | G78: 2025-04-23 | H78: Paid | I78: 2565.06 | J78: 0 | K78: 7 | L78: Current | N78: =FALSE() -> FALSE | O78: 0 | P78: 0 | Q78: =FALSE() -> FALSE | R78: =FALSE() -> FALSE
A79: INV-1078 | B79: Northside Transport | C79: US02 | D79: Apr-25 | E79: 2025-04-20 | F79: 2025-05-21 | G79: 2025-05-28 | H79: Paid | I79: 1598.27 | J79: 0 | K79: 37 | L79: Current | N79: =TRUE() -> TRUE | O79: 0 | P79: 0 | Q79: =FALSE() -> FALSE | R79: =FALSE() -> FALSE | S79: Late Payment | T79: Yellow
A80: INV-1079 | B80: IT Services Group | C80: US01 | D80: Apr-25 | E80: 2025-04-20 | F80: 2025-06-05 | G80: 2025-05-24 | H80: Paid | I80: 1930.38 | J80: 0 | K80: 33 | L80: Current | N80: =FALSE() -> FALSE | O80: 0 | P80: 0 | Q80: =FALSE() -> FALSE | R80: =FALSE() -> FALSE
A81: INV-1080 | B81: Alpha Facilities Mgmt | C81: US03 | D81: Apr-25 | E81: 2025-04-21 | F81: 2025-05-22 | H81: Overdue | I81: 669.31 | J81: 669.31 | L81: 31-60 Days | M81: 39 | N81: =FALSE() -> FALSE | O81: 0 | P81: 0 | Q81: =FALSE() -> FALSE | R81: =FALSE() -> FALSE | S81: Overdue Invoice | T81: Red
A82: INV-1081 | B82: Logistics Partners | C82: US02 | D82: Apr-25 | E82: 2025-04-22 | F82: 2025-05-23 | H82: Blocked | I82: 1612.56 | J82: 1612.56 | L82: 31-60 Days | M82: 38 | N82: =FALSE() -> FALSE | O82: 0 | P82: 0 | Q82: =TRUE() -> TRUE | R82: =FALSE() -> FALSE | S82: Blocked Over 30 Days | T82: Red
A83: INV-1082 | B83: Packaging World | C83: US02 | D83: Apr-25 | E83: 2025-04-22 | F83: 2025-05-23 | G83: 2025-05-28 | H83: Paid | I83: 838.35 | J83: 0 | K83: 35 | L83: Current | N83: =TRUE() -> TRUE | O83: 0 | P83: 0 | Q83: =FALSE() -> FALSE | R83: =FALSE() -> FALSE | S83: Late Payment | T83: Yellow
A84: INV-1083 | B84: West Coast Paper | C84: US01 | D84: Apr-25 | E84: 2025-04-22 | F84: 2025-05-08 | H84: In Review | I84: 205.09 | J84: 205.09 | L84: 31-60 Days | M84: 53 | N84: =FALSE() -> FALSE | O84: 0 | P84: 0 | Q84: =FALSE() -> FALSE | R84: =TRUE() -> TRUE | S84: In Review Over 15 Days | T84: Amber
A85: INV-1084 | B85: Continental Freight | C85: US02 | D85: Apr-25 | E85: 2025-04-23 | F85: 2025-05-24 | H85: Overdue | I85: 2921.55 | J85: 2921.55 | L85: 31-60 Days | M85: 37 | N85: =FALSE() -> FALSE | O85: 0 | P85: 58.43 | Q85: =FALSE() -> FALSE | R85: =FALSE() -> FALSE | S85: Missed Discount | T85: Amber
A86: INV-1085 | B86: Northside Transport | C86: US02 | D86: Apr-25 | E86: 2025-04-25 | F86: 2025-05-28 | G86: 2025-05-13 | H86: Paid | I86: 2437.99 | J86: 0 | K86: 15 | L86: Current | N86: =FALSE() -> FALSE | O86: 0 | P86: 0 | Q86: =FALSE() -> FALSE | R86: =FALSE() -> FALSE
A87: INV-1086 | B87: Cleaning Solutions | C87: US02 | D87: Apr-25 | E87: 2025-04-26 | F87: 2025-05-28 | G87: 2025-05-12 | H87: Paid | I87: 565.3 | J87: 0 | K87: 14 | L87: Current | N87: =FALSE() -> FALSE | O87: 0 | P87: 0 | Q87: =FALSE() -> FALSE | R87: =FALSE() -> FALSE
A88: INV-1087 | B88: Northside Transport | C88: US02 | D88: May-25 | E88: 2025-05-05 | F88: 2025-06-05 | G88: 2025-05-12 | H88: Paid | I88: 2943.09 | J88: 0 | K88: 6 | L88: Current | N88: =FALSE() -> FALSE | O88: 0 | P88: 0 | Q88: =FALSE() -> FALSE | R88: =FALSE() -> FALSE
A89: INV-1088 | B89: Suministros MX | C89: MX01 | D89: May-25 | E89: 2025-05-06 | F89: 2025-06-06 | G89: 2025-06-15 | H89: Paid | I89: 536.29 | J89: 0 | K89: 39 | L89: Current | N89: =TRUE() -> TRUE | O89: 0 | P89: 0 | Q89: =FALSE() -> FALSE | R89: =FALSE() -> FALSE | S89: Late Payment | T89: Yellow
A90: INV-1089 | B90: IT Services Group | C90: US01 | D90: May-25 | E90: 2025-05-07 | F90: 2025-06-22 | H90: In Review | I90: 1928.55 | J90: 1928.55 | L90: 0-30 Days | M90: 8 | N90: =FALSE() -> FALSE | O90: 0 | P90: 0 | Q90: =FALSE() -> FALSE | R90: =TRUE() -> TRUE | S90: In Review Over 15 Days | T90: Amber
A91: INV-1090 | B91: Alpha Facilities Mgmt | C91: US03 | D91: May-25 | E91: 2025-05-08 | F91: 2025-06-08 | G91: 2025-06-12 | H91: Paid | I91: 671.56 | J91: 0 | K91: 34 | L91: Current | N91: =TRUE() -> TRUE | O91: 0 | P91: 0 | Q91: =FALSE() -> FALSE | R91: =FALSE() -> FALSE | S91: Late Payment | T91: Yellow
A92: INV-1091 | B92: Logistics Partners | C92: US02 | D92: May-25 | E92: 2025-05-10 | F92: 2025-06-11 | G92: 2025-06-04 | H92: Paid | I92: 2616.55 | J92: 0 | K92: 23 | L92: Current | N92: =FALSE() -> FALSE | O92: 0 | P92: 0 | Q92: =FALSE() -> FALSE | R92: =FALSE() -> FALSE
A93: INV-1092 | B93: Northside Transport | C93: US02 | D93: May-25 | E93: 2025-05-11 | F93: 2025-06-11 | G93: 2025-06-19 | H93: Paid | I93: 1197.86 | J93: 0 | K93: 38 | L93: Current | N93: =TRUE() -> TRUE | O93: 0 | P93: 0 | Q93: =FALSE() -> FALSE | R93: =FALSE() -> FALSE | S93: Late Payment | T93: Yellow
A94: INV-1093 | B94: Office Supply Co | C94: US01 | D94: May-25 | E94: 2025-05-14 | F94: 2025-06-14 | H94: Overdue | I94: 405.64 | J94: 405.64 | L94: 0-30 Days | M94: 16 | N94: =FALSE() -> FALSE | O94: 0 | P94: 0 | Q94: =FALSE() -> FALSE | R94: =FALSE() -> FALSE | S94: Overdue Invoice | T94: Red
A95: INV-1094 | B95: IT Services Group | C95: US01 | D95: May-25 | E95: 2025-05-16 | F95: 2025-07-03 | G95: 2025-05-27 | H95: Paid | I95: 2106.43 | J95: 0 | K95: 8 | L95: Current | N95: =FALSE() -> FALSE | O95: 0 | P95: 0 | Q95: =FALSE() -> FALSE | R95: =FALSE() -> FALSE
A96: INV-1095 | B96: Logistics Partners | C96: US02 | D96: May-25 | E96: 2025-05-18 | F96: 2025-06-18 | G96: 2025-06-02 | H96: Paid | I96: 1324.98 | J96: 0 | K96: 14 | L96: Current | N96: =FALSE() -> FALSE | O96: 0 | P96: 0 | Q96: =FALSE() -> FALSE | R96: =FALSE() -> FALSE
A97: INV-1096 | B97: Cleaning Solutions | C97: US02 | D97: May-25 | E97: 2025-05-18 | F97: 2025-06-18 | H97: Blocked | I97: 539.79 | J97: 539.79 | L97: 0-30 Days | M97: 12 | N97: =FALSE() -> FALSE | O97: 0 | P97: 0 | Q97: =TRUE() -> TRUE | R97: =FALSE() -> FALSE | S97: Blocked Over 30 Days | T97: Red
A98: INV-1097 | B98: Metro Packaging | C98: US02 | D98: May-25 | E98: 2025-05-18 | F98: 2025-06-18 | G98: 2025-05-24 | H98: Partially Paid | I98: 518.06 | J98: 207.22 | L98: 0-30 Days | M98: 12 | N98: =FALSE() -> FALSE | O98: 0 | P98: 10.36 | Q98: =FALSE() -> FALSE | R98: =FALSE() -> FALSE | S98: Missed Discount | T98: Amber
A99: INV-1098 | B99: Continental Freight | C99: US02 | D99: May-25 | E99: 2025-05-18 | F99: 2025-06-18 | G99: 2025-06-14 | H99: Paid | I99: 3210.18 | J99: 0 | K99: 26 | L99: Current | N99: =FALSE() -> FALSE | O99: 0 | P99: 64.2 | Q99: =FALSE() -> FALSE | R99: =FALSE() -> FALSE | S99: Missed Discount | T99: Amber
A100: INV-1099 | B100: Office Supply Co | C100: US01 | D100: May-25 | E100: 2025-05-21 | F100: 2025-06-21 | H100: Overdue | I100: 489.21 | J100: 489.21 | L100: 0-30 Days | M100: 9 | N100: =FALSE() -> FALSE | O100: 0 | P100: 0 | Q100: =FALSE() -> FALSE | R100: =FALSE() -> FALSE | S100: Overdue Invoice | T100: Red
...

Sheet Dashboard
B2: AP Management Dashboard
B3: Accounts Payable Operations · Jan – Jun 2025 · Project by Augusto Sander
B7: TOTAL OUTSTANDING (USD) | G7: ON-TIME PAYMENT RATE | M7: DISCOUNT CAPTURE RATE | R7: CRITICAL EXCEPTIONS
B8: ='Summary Tables'!D5 -> 77420.62 | G8: ='Summary Tables'!D7 -> 0.83098592 | M8: ='Summary Tables'!D8 -> 0.033716126 | R8: ='Summary Tables'!D9 -> 14
B9: =TEXT('Summary Tables'!D6,"0")&" invoices open" -> 61 invoices open | G9: "Target ≥ 85%" | M9: ="$"&TEXT('Summary Tables'!D10,"#,##0")&" in missed savings" -> $552 in missed savings | R9: "Blocked 30d · Voided · In Review"

Sheet Exceptions Detail
B1: Exceptions Detail
B3: Critical exception breakdown by type and company code · 14 total exceptions across 3 categories
B4: ▸ BY EXCEPTION TYPE · Company breakdown
B5: Exception Type | C5: Total | D5: US01 | E5: US02 | F5: MX01 | G5: US03 | H5: What it means
B6: Blocked 30d+ | C6: ='Summary Tables'!C58 -> 7 | D6: ='Summary Tables'!D58 -> 2 | E6: ='Summary Tables'!E58 -> 4 | F6: ='Summary Tables'!F58 -> 1 | G6: ='Summary Tables'!G58 -> 0 | H6: Invoice has been blocked from payment for 30+ days — requires urgent review
B7: In Review 15d+ | C7: ='Summary Tables'!C59 -> 4 | D7: ='Summary Tables'!D59 -> 2 | E7: ='Summary Tables'!E59 -> 2 | F7: ='Summary Tables'!F59 -> 0 | G7: ='Summary Tables'!G59 -> 0 | H7: Invoice stuck in review queue for 15+ days — SLA breach
B8: Voided | C8: ='Summary Tables'!C60 -> 3 | D8: ='Summary Tables'!D60 -> 0 | E8: ='Summary Tables'!E60 -> 2 | F8: ='Summary Tables'!F60 -> 1 | G8: ='Summary Tables'!G60 -> 0 | H8: Invoice voided — may indicate duplicate, error, or dispute
B9: TOTAL EXCEPTIONS | C9: ='Summary Tables'!D9 -> 14
B11: ▸ BY VENDOR · Which vendors are driving exceptions
B12: Vendor | C12: Blocked 30d+ | D12: In Review 15d+ | E12: Voided | F12: Total
B13: Fresh Beverages Inc | C13: =COUNTIFS(AP_Invoices[Vendor],B13,AP_Invoices[Blocked 30d],TRUE()) -> 0 | D13: =COUNTIFS(AP_Invoices[Vendor],B13,AP_Invoices[In Review 15d],TRUE()) -> 0 | E13: =COUNTIFS(AP_Invoices[Vendor],B13,AP_Invoices[Status],"Voided") -> 0 | F13: =SUM(C13:E13) -> 0
B14: Continental Freight | C14: =COUNTIFS(AP_Invoices[Vendor],B14,AP_Invoices[Blocked 30d],TRUE()) -> 1 | D14: =COUNTIFS(AP_Invoices[Vendor],B14,AP_Invoices[In Review 15d],TRUE()) -> 0 | E14: =COUNTIFS(AP_Invoices[Vendor],B14,AP_Invoices[Status],"Voided") -> 0 | F14: =SUM(C14:E14) -> 1
B15: IT Services Group | C15: =COUNTIFS(AP_Invoices[Vendor],B15,AP_Invoices[Blocked 30d],TRUE()) -> 0 | D15: =COUNTIFS(AP_Invoices[Vendor],B15,AP_Invoices[In Review 15d],TRUE()) -> 1 | E15: =COUNTIFS(AP_Invoices[Vendor],B15,AP_Invoices[Status],"Voided") -> 0 | F15: =SUM(C15:E15) -> 1
B16: Vendor One Foods | C16: =COUNTIFS(AP_Invoices[Vendor],B16,AP_Invoices[Blocked 30d],TRUE()) -> 0 | D16: =COUNTIFS(AP_Invoices[Vendor],B16,AP_Invoices[In Review 15d],TRUE()) -> 0 | E16: =COUNTIFS(AP_Invoices[Vendor],B16,AP_Invoices[Status],"Voided") -> 0 | F16: =SUM(C16:E16) -> 0
B17: Logistics Partners | C17: =COUNTIFS(AP_Invoices[Vendor],B17,AP_Invoices[Blocked 30d],TRUE()) -> 2 | D17: =COUNTIFS(AP_Invoices[Vendor],B17,AP_Invoices[In Review 15d],TRUE()) -> 0 | E17: =COUNTIFS(AP_Invoices[Vendor],B17,AP_Invoices[Status],"Voided") -> 0 | F17: =SUM(C17:E17) -> 2
B18: EuroFreight GmbH | C18: =COUNTIFS(AP_Invoices[Vendor],B18,AP_Invoices[Blocked 30d],TRUE()) -> 0 | D18: =COUNTIFS(AP_Invoices[Vendor],B18,AP_Invoices[In Review 15d],TRUE()) -> 0 | E18: =COUNTIFS(AP_Invoices[Vendor],B18,AP_Invoices[Status],"Voided") -> 0 | F18: =SUM(C18:E18) -> 0
B19: Metro Packaging | C19: =COUNTIFS(AP_Invoices[Vendor],B19,AP_Invoices[Blocked 30d],TRUE()) -> 0 | D19: =COUNTIFS(AP_Invoices[Vendor],B19,AP_Invoices[In Review 15d],TRUE()) -> 1 | E19: =COUNTIFS(AP_Invoices[Vendor],B19,AP_Invoices[Status],"Voided") -> 0 | F19: =SUM(C19:E19) -> 1
B20: Northside Transport | C20: =COUNTIFS(AP_Invoices[Vendor],B20,AP_Invoices[Blocked 30d],TRUE()) -> 0 | D20: =COUNTIFS(AP_Invoices[Vendor],B20,AP_Invoices[In Review 15d],TRUE()) -> 0 | E20: =COUNTIFS(AP_Invoices[Vendor],B20,AP_Invoices[Status],"Voided") -> 0 | F20: =SUM(C20:E20) -> 0
B21: City Utilities | C21: =COUNTIFS(AP_Invoices[Vendor],B21,AP_Invoices[Blocked 30d],TRUE()) -> 1 | D21: =COUNTIFS(AP_Invoices[Vendor],B21,AP_Invoices[In Review 15d],TRUE()) -> 0 | E21: =COUNTIFS(AP_Invoices[Vendor],B21,AP_Invoices[Status],"Voided") -> 0 | F21: =SUM(C21:E21) -> 1
B22: Suministros MX | C22: =COUNTIFS(AP_Invoices[Vendor],B22,AP_Invoices[Blocked 30d],TRUE()) -> 1 | D22: =COUNTIFS(AP_Invoices[Vendor],B22,AP_Invoices[In Review 15d],TRUE()) -> 0 | E22: =COUNTIFS(AP_Invoices[Vendor],B22,AP_Invoices[Status],"Voided") -> 1 | F22: =SUM(C22:E22) -> 2
B23: Packaging World | C23: =COUNTIFS(AP_Invoices[Vendor],B23,AP_Invoices[Blocked 30d],TRUE()) -> 0 | D23: =COUNTIFS(AP_Invoices[Vendor],B23,AP_Invoices[In Review 15d],TRUE()) -> 1 | E23: =COUNTIFS(AP_Invoices[Vendor],B23,AP_Invoices[Status],"Voided") -> 1 | F23: =SUM(C23:E23) -> 2
B24: Office Supply Co | C24: =COUNTIFS(AP_Invoices[Vendor],B24,AP_Invoices[Blocked 30d],TRUE()) -> 0 | D24: =COUNTIFS(AP_Invoices[Vendor],B24,AP_Invoices[In Review 15d],TRUE()) -> 0 | E24: =COUNTIFS(AP_Invoices[Vendor],B24,AP_Invoices[Status],"Voided") -> 0 | F24: =SUM(C24:E24) -> 0
... B27: Cleaning Solutions | C27: =COUNTIFS(AP_Invoices[Vendor],B27,AP_Invoices[Blocked 30d],TRUE()) -> 1 | D27: =COUNTIFS(AP_Invoices[Vendor],B27,AP_Invoices[In Review 15d],TRUE()) -> 0 | E27: =COUNTIFS(AP_Invoices[Vendor],B27,AP_Invoices[Status],"Voided") -> 1 | F27: =SUM(C27:E27) -> 2

Sheet Summary Tables
B1: Summary Tables — Excel Formula Engine
B3: ► KPI METRICS
B4: Metric | C4: Excel Formula | D4: Result
B5: Total Outstanding (USD) | C5: =SUM(AP_Invoices[Outstanding USD]) -> 77420.62 | D5: =SUM(AP_Invoices[Outstanding USD]) -> 77420.62 | E5: Sum of all unpaid balances
B6: Unpaid Invoice Count | C6: =COUNTIF(AP_Invoices[Outstanding USD],">"&0) -> 61 | D6: =COUNTIF(AP_Invoices[Outstanding USD],">"&0) -> 61 | E6: Invoices with outstanding > 0
B7: On-Time Payment Rate | C7: =(COUNTIFS(AP_Invoices[Late Payment],FALSE(),AP_Invoices[Status],"Paid")+COUNTIFS(AP_Invoices[Late Payment],FALSE(),AP_Invoices[Status],"Partially Paid"))/(COUNTIF(AP_Invoices[Status],"Paid")+COUNTIF(AP_Invoices[Status],"Partially Paid")) -> 0.83098592 | D7: =(COUNTIFS(AP_Invoices[Late Payment],FALSE(),AP_Invoices[Status],"Paid")+COUNTIFS(AP_Invoices[Late Payment],FALSE(),AP_Invoices[Status],"Partially Paid"))/(COUNTIF(AP_Invoices[Status],"Paid")+COUNTIF(AP_Invoices[Status],"Partially Paid")) -> 0.83098592 | E7: Paid invoices where late_payment_flag = FALSE
B8: Discount Capture Rate | C8: =SUM(AP_Invoices[Disc Captured])/(SUM(AP_Invoices[Disc Captured])+SUM(AP_Invoices[Disc Missed])) -> 0.033716126 | D8: =SUM(AP_Invoices[Disc Captured])/(SUM(AP_Invoices[Disc Captured])+SUM(AP_Invoices[Disc Missed])) -> 0.033716126 | E8: Captured ÷ (Captured + Missed)
B9: Critical Exceptions | C9: =COUNTIF(AP_Invoices[Blocked 30d],TRUE())+COUNTIF(AP_Invoices[Status],"Voided")+COUNTIF(AP_Invoices[In Review 15d],TRUE()) -> 14 | D9: =COUNTIF(AP_Invoices[Blocked 30d],TRUE())+COUNTIF(AP_Invoices[Status],"Voided")+COUNTIF(AP_Invoices[In Review 15d],TRUE()) -> 14 | E9: Blocked 30d + Voided + In Review 15d
B10: Total Missed Discount (USD) | C10: =SUM(AP_Invoices[Disc Missed]) -> 551.98 | D10: =SUM(AP_Invoices[Disc Missed]) -> 551.98 | E10: Used in KPI badge
B12: ► AGING BREAKDOWN — source for Aging chart
B13: Aging Bucket | C13: Outstanding USD
B14: Current | C14: =SUMIF(AP_Invoices[Aging Bucket],B14,AP_Invoices[Outstanding USD]) -> 22996.67
B15: 0-30 Days | C15: =SUMIF(AP_Invoices[Aging Bucket],B15,AP_Invoices[Outstanding USD]) -> 8047.98
B16: 31-60 Days | C16: =SUMIF(AP_Invoices[Aging Bucket],B16,AP_Invoices[Outstanding USD]) -> 13989.01
B17: 61-90 Days | C17: =SUMIF(AP_Invoices[Aging Bucket],B17,AP_Invoices[Outstanding USD]) -> 21000.23
B18: 90+ Days | C18: =SUMIF(AP_Invoices[Aging Bucket],B18,AP_Invoices[Outstanding USD]) -> 11386.73
B20: ► DISCOUNT BY MONTH — source for Discount chart
B21: Month | C21: Captured USD | D21: Missed USD
B22: Jan-25 | C22: =SUMIF(AP_Invoices[Month],B22,AP_Invoices[Disc Captured]) -> 19.26 | D22: =SUMIF(AP_Invoices[Month],B22,AP_Invoices[Disc Missed]) -> 130.27
B23: Feb-25 | C23: =SUMIF(AP_Invoices[Month],B23,AP_Invoices[Disc Captured]) -> 0 | D23: =SUMIF(AP_Invoices[Month],B23,AP_Invoices[Disc Missed]) -> 82.49
B24: Mar-25 | C24: =SUMIF(AP_Invoices[Month],B24,AP_Invoices[Disc Captured]) -> 0 | D24: =SUMIF(AP_Invoices[Month],B24,AP_Invoices[Disc Missed]) -> 85.69
B25: Apr-25 | C25: =SUMIF(AP_Invoices[Month],B25,AP_Invoices[Disc Captured]) -> 0 | D25: =SUMIF(AP_Invoices[Month],B25,AP_Invoices[Disc Missed]) -> 80.82
B26: May-25 | C26: =SUMIF(AP_Invoices[Month],B26,AP_Invoices[Disc Captured]) -> 0 | D26: =SUMIF(AP_Invoices[Month],B26,AP_Invoices[Disc Missed]) -> 115.21
B27: Jun-25 | C27: =SUMIF(AP_Invoices[Month],B27,AP_Invoices[Disc Captured]) -> 0 | D27: =SUMIF(AP_Invoices[Month],B27,AP_Invoices[Disc Missed]) -> 57.5
B29: ▸ ► ON-TIME RATE BY MONTH — source for Trend chart
B30: Month | C30: Paid On-Time | D30: Total Paid | E30: On-Time Rate %
B31: Jan-25 | C31: =COUNTIFS(AP_Invoices[Month],B31,AP_Invoices[Late Payment],FALSE(),AP_Invoices[Status],"Paid") -> 12 | D31: =COUNTIFS(AP_Invoices[Month],B31,AP_Invoices[Status],"Paid") -> 14 | E31: =IF(D31>0,C31/D31,0) -> 0.85714286
B32: Feb-25 | C32: =COUNTIFS(AP_Invoices[Month],B32,AP_Invoices[Late Payment],FALSE(),AP_Invoices[Status],"Paid") -> 11 | D32: =COUNTIFS(AP_Invoices[Month],B32,AP_Invoices[Status],"Paid") -> 12 | E32: =IF(D32>0,C32/D32,0) -> 0.91666667
B33: Mar-25 | C33: =COUNTIFS(AP_Invoices[Month],B33,AP_Invoices[Late Payment],FALSE(),AP_Invoices[Status],"Paid") -> 6 | D33: =COUNTIFS(AP_Invoices[Month],B33,AP_Invoices[Status],"Paid") -> 9 | E33: =IF(D33>0,C33/D33,0) -> 0.66666667
B34: Apr-25 | C34: =COUNTIFS(AP_Invoices[Month],B34,AP_Invoices[Late Payment],FALSE(),AP_Invoices[Status],"Paid") -> 9 | D34: =COUNTIFS(AP_Invoices[Month],B34,AP_Invoices[Status],"Paid") -> 12 | E34: =IF(D34>0,C34/D34,0) -> 0.75
B35: May-25 | C35: =COUNTIFS(AP_Invoices[Month],B35,AP_Invoices[Late Payment],FALSE(),AP_Invoices[Status],"Paid") -> 10 | D35: =COUNTIFS(AP_Invoices[Month],B35,AP_Invoices[Status],"Paid") -> 13 | E35: =IF(D35>0,C35/D35,0) -> 0.76923077
B36: Jun-25 | C36: =COUNTIFS(AP_Invoices[Month],B36,AP_Invoices[Late Payment],FALSE(),AP_Invoices[Status],"Paid") -> 6 | D36: =COUNTIFS(AP_Invoices[Month],B36,AP_Invoices[Status],"Paid") -> 6 | E36: =IF(D36>0,C36/D36,0) -> 1
B38: ▸ ► VENDOR SUMMARY — source for Vendor Analysis tab
B39: Vendor | C39: Outstanding USD | D39: Invoice Count | E39: Overdue Count | F39: Disc Missed USD | G39: Exceptions
B40: Fresh Beverages Inc | C40: =SUMIF(AP_Invoices[Vendor],B40,AP_Invoices[Outstanding USD]) -> 13779.17 | D40: =COUNTIF(AP_Invoices[Vendor],B40) -> 9 | E40: =COUNTIFS(AP_Invoices[Vendor],B40,AP_Invoices[Status],"Overdue")+COUNTIFS(AP_Invoices[Vendor],B40,AP_Invoices[Status],"Blocked")+COUNTIFS(AP_Invoices[Vendor],B40,AP_Invoices[Status],"In Review")+COUNTIFS(AP_Invoices[Vendor],B40,AP_Invoices[Status],"Partially Paid",AP_Invoices[Days Past Due],">"&0) -> 3 | F40: =SUMIF(AP_Invoices[Vendor],B40,AP_Invoices[Disc Missed]) -> 0 | G40: =COUNTIFS(AP_Invoices[Vendor],B40,AP_Invoices[Blocked 30d],TRUE())+COUNTIFS(AP_Invoices[Vendor],B40,AP_Invoices[Status],"Voided")+COUNTIFS(AP_Invoices[Vendor],B40,AP_Invoices[In Review 15d],TRUE()) -> 0
B41: Continental Freight | C41: =SUMIF(AP_Invoices[Vendor],B41,AP_Invoices[Outstanding USD]) -> 11030.14 | D41: =COUNTIF(AP_Invoices[Vendor],B41) -> 9 | E41: =COUNTIFS(AP_Invoices[Vendor],B41,AP_Invoices[Status],"Overdue")+COUNTIFS(AP_Invoices[Vendor],B41,AP_Invoices[Status],"Blocked")+COUNTIFS(AP_Invoices[Vendor],B41,AP_Invoices[Status],"In Review")+COUNTIFS(AP_Invoices[Vendor],B41,AP_Invoices[Status],"Partially Paid",AP_Invoices[Days Past Due],">"&0) -> 4 | F41: =SUMIF(AP_Invoices[Vendor],B41,AP_Invoices[Disc Missed]) -> 451.08 | G41: =COUNTIFS(AP_Invoices[Vendor],B41,AP_Invoices[Blocked 30d],TRUE())+COUNTIFS(AP_Invoices[Vendor],B41,AP_Invoices[Status],"Voided")+COUNTIFS(AP_Invoices[Vendor],B41,AP_Invoices[In Review 15d],TRUE()) -> 1
B42: IT Services Group | C42: =SUMIF(AP_Invoices[Vendor],B42,AP_Invoices[Outstanding USD]) -> 8700.57 | D42: =COUNTIF(AP_Invoices[Vendor],B42) -> 9 | E42: =COUNTIFS(AP_Invoices[Vendor],B42,AP_Invoices[Status],"Overdue")+COUNTIFS(AP_Invoices[Vendor],B42,AP_Invoices[Status],"Blocked")+COUNTIFS(AP_Invoices[Vendor],B42,AP_Invoices[Status],"In Review")+COUNTIFS(AP_Invoices[Vendor],B42,AP_Invoices[Status],"Partially Paid",AP_Invoices[Days Past Due],">"&0) -> 4 | F42: =SUMIF(AP_Invoices[Vendor],B42,AP_Invoices[Disc Missed]) -> 0 | G42: =COUNTIFS(AP_Invoices[Vendor],B42,AP_Invoices[Blocked 30d],TRUE())+COUNTIFS(AP_Invoices[Vendor],B42,AP_Invoices[Status],"Voided")+COUNTIFS(AP_Invoices[Vendor],B42,AP_Invoices[In Review 15d],TRUE()) -> 1
B43: Vendor One Foods | C43: =SUMIF(AP_Invoices[Vendor],B43,AP_Invoices[Outstanding USD]) -> 7208.24 | D43: =COUNTIF(AP_Invoices[Vendor],B43) -> 9 | E43: =COUNTIFS(AP_Invoices[Vendor],B43,AP_Invoices[Status],"Overdue")+COUNTIFS(AP_Invoices[Vendor],B43,AP_Invoices[Status],"Blocked")+COUNTIFS(AP_Invoices[Vendor],B43,AP_Invoices[Status],"In Review")+COUNTIFS(AP_Invoices[Vendor],B43,AP_Invoices[Status],"Partially Paid",AP_Invoices[Days Past Due],">"&0) -> 2 | F43: =SUMIF(AP_Invoices[Vendor],B43,AP_Invoices[Disc Missed]) -> 0 | G43: =COUNTIFS(AP_Invoices[Vendor],B43,AP_Invoices[Blocked 30d],TRUE())+COUNTIFS(AP_Invoices[Vendor],B43,AP_Invoices[Status],"Voided")+COUNTIFS(AP_Invoices[Vendor],B43,AP_Invoices[In Review 15d],TRUE()) -> 0
B44: Logistics Partners | C44: =SUMIF(AP_Invoices[Vendor],B44,AP_Invoices[Outstanding USD]) -> 6447.85 | D44: =COUNTIF(AP_Invoices[Vendor],B44) -> 10 | E44: =COUNTIFS(AP_Invoices[Vendor],B44,AP_Invoices[Status],"Overdue")+COUNTIFS(AP_Invoices[Vendor],B44,AP_Invoices[Status],"Blocked")+COUNTIFS(AP_Invoices[Vendor],B44,AP_Invoices[Status],"In Review")+COUNTIFS(AP_Invoices[Vendor],B44,AP_Invoices[Status],"Partially Paid",AP_Invoices[Days Past Due],">"&0) -> 2 | F44: =SUMIF(AP_Invoices[Vendor],B44,AP_Invoices[Disc Missed]) -> 0 | G44: =COUNTIFS(AP_Invoices[Vendor],B44,AP_Invoices[Blocked 30d],TRUE())+COUNTIFS(AP_Invoices[Vendor],B44,AP_Invoices[Status],"Voided")+COUNTIFS(AP_Invoices[Vendor],B44,AP_Invoices[In Review 15d],TRUE()) -> 2
B45: EuroFreight GmbH | C45: =SUMIF(AP_Invoices[Vendor],B45,AP_Invoices[Outstanding USD]) -> 5696.25 | D45: =COUNTIF(AP_Invoices[Vendor],B45) -> 6 | E45: =COUNTIFS(AP_Invoices[Vendor],B45,AP_Invoices[Status],"Overdue")+COUNTIFS(AP_Invoices[Vendor],B45,AP_Invoices[Status],"Blocked")+COUNTIFS(AP_Invoices[Vendor],B45,AP_Invoices[Status],"In Review")+COUNTIFS(AP_Invoices[Vendor],B45,AP_Invoices[Status],"Partially Paid",AP_Invoices[Days Past Due],">"&0) -> 2 | F45: =SUMIF(AP_Invoices[Vendor],B45,AP_Invoices[Disc Missed]) -> 0 | G45: =COUNTIFS(AP_Invoices[Vendor],B45,AP_Invoices[Blocked 30d],TRUE())+COUNTIFS(AP_Invoices[Vendor],B45,AP_Invoices[Status],"Voided")+COUNTIFS(AP_Invoices[Vendor],B45,AP_Invoices[In Review 15d],TRUE()) -> 0
B46: Metro Packaging | C46: =SUMIF(AP_Invoices[Vendor],B46,AP_Invoices[Outstanding USD]) -> 4829.39 | D46: =COUNTIF(AP_Invoices[Vendor],B46) -> 8 | E46: =COUNTIFS(AP_Invoices[Vendor],B46,AP_Invoices[Status],"Overdue")+COUNTIFS(AP_Invoices[Vendor],B46,AP_Invoices[Status],"Blocked")+COUNTIFS(AP_Invoices[Vendor],B46,AP_Invoices[Status],"In Review")+COUNTIFS(AP_Invoices[Vendor],B46,AP_Invoices[Status],"Partially Paid",AP_Invoices[Days Past Due],">"&0) -> 4 | F46: =SUMIF(AP_Invoices[Vendor],B46,AP_Invoices[Disc Missed]) -> 100.9 | G46: =COUNTIFS(AP_Invoices[Vendor],B46,AP_Invoices[Blocked 30d],TRUE())+COUNTIFS(AP_Invoices[Vendor],B46,AP_Invoices[Status],"Voided")+COUNTIFS(AP_Invoices[Vendor],B46,AP_Invoices[In Review 15d],TRUE()) -> 1
B47: Northside Transport | C47: =SUMIF(AP_Invoices[Vendor],B47,AP_Invoices[Outstanding USD]) -> 3607.89 | D47: =COUNTIF(AP_Invoices[Vendor],B47) -> 9 | E47: =COUNTIFS(AP_Invoices[Vendor],B47,AP_Invoices[Status],"Overdue")+COUNTIFS(AP_Invoices[Vendor],B47,AP_Invoices[Status],"Blocked")+COUNTIFS(AP_Invoices[Vendor],B47,AP_Invoices[Status],"In Review")+COUNTIFS(AP_Invoices[Vendor],B47,AP_Invoices[Status],"Partially Paid",AP_Invoices[Days Past Due],">"&0) -> 1 | F47: =SUMIF(AP_Invoices[Vendor],B47,AP_Invoices[Disc Missed]) -> 0 | G47: =COUNTIFS(AP_Invoices[Vendor],B47,AP_Invoices[Blocked 30d],TRUE())+COUNTIFS(AP_Invoices[Vendor],B47,AP_Invoices[Status],"Voided")+COUNTIFS(AP_Invoices[Vendor],B47,AP_Invoices[In Review 15d],TRUE()) -> 0
B48: City Utilities | C48: =SUMIF(AP_Invoices[Vendor],B48,AP_Invoices[Outstanding USD]) -> 3052.83 | D48: =COUNTIF(AP_Invoices[Vendor],B48) -> 10 | E48: =COUNTIFS(AP_Invoices[Vendor],B48,AP_Invoices[Status],"Overdue")+COUNTIFS(AP_Invoices[Vendor],B48,AP_Invoices[Status],"Blocked")+COUNTIFS(AP_Invoices[Vendor],B48,AP_Invoices[Status],"In Review")+COUNTIFS(AP_Invoices[Vendor],B48,AP_Invoices[Status],"Partially Paid",AP_Invoices[Days Past Due],">"&0) -> 5 | F48: =SUMIF(AP_Invoices[Vendor],B48,AP_Invoices[Disc Missed]) -> 0 | G48: =COUNTIFS(AP_Invoices[Vendor],B48,AP_Invoices[Blocked 30d],TRUE())+COUNTIFS(AP_Invoices[Vendor],B48,AP_Invoices[Status],"Voided")+COUNTIFS(AP_Invoices[Vendor],B48,AP_Invoices[In Review 15d],TRUE()) -> 1
B49: Suministros MX | C49: =SUMIF(AP_Invoices[Vendor],B49,AP_Invoices[Outstanding USD]) -> 2740.86 | D49: =COUNTIF(AP_Invoices[Vendor],B49) -> 6 | E49: =COUNTIFS(AP_Invoices[Vendor],B49,AP_Invoices[Status],"Overdue")+COUNTIFS(AP_Invoices[Vendor],B49,AP_Invoices[Status],"Blocked")+COUNTIFS(AP_Invoices[Vendor],B49,AP_Invoices[Status],"In Review")+COUNTIFS(AP_Invoices[Vendor],B49,AP_Invoices[Status],"Partially Paid",AP_Invoices[Days Past Due],">"&0) -> 3 | F49: =SUMIF(AP_Invoices[Vendor],B49,AP_Invoices[Disc Missed]) -> 0 | G49: =COUNTIFS(AP_Invoices[Vendor],B49,AP_Invoices[Blocked 30d],TRUE())+COUNTIFS(AP_Invoices[Vendor],B49,AP_Invoices[Status],"Voided")+COUNTIFS(AP_Invoices[Vendor],B49,AP_Invoices[In Review 15d],TRUE()) -> 2
B50: Packaging World | C50: =SUMIF(AP_Invoices[Vendor],B50,AP_Invoices[Outstanding USD]) -> 2493.11 | D50: =COUNTIF(AP_Invoices[Vendor],B50) -> 10 | E50: =COUNTIFS(AP_Invoices[Vendor],B50,AP_Invoices[Status],"Overdue")+COUNTIFS(AP_Invoices[Vendor],B50,AP_Invoices[Status],"Blocked")+COUNTIFS(AP_Invoices[Vendor],B50,AP_Invoices[Status],"In Review")+COUNTIFS(AP_Invoices[Vendor],B50,AP_Invoices[Status],"Partially Paid",AP_Invoices[Days Past Due],">"&0) -> 3 | F50: =SUMIF(AP_Invoices[Vendor],B50,AP_Invoices[Disc Missed]) -> 0 | G50: =COUNTIFS(AP_Invoices[Vendor],B50,AP_Invoices[Blocked 30d],TRUE())+COUNTIFS(AP_Invoices[Vendor],B50,AP_Invoices[Status],"Voided")+COUNTIFS(AP_Invoices[Vendor],B50,AP_Invoices[In Review 15d],TRUE()) -> 2
B51: Office Supply Co | C51: =SUMIF(AP_Invoices[Vendor],B51,AP_Invoices[Outstanding USD]) -> 2483.09 | D51: =COUNTIF(AP_Invoices[Vendor],B51) -> 10 | E51: =COUNTIFS(AP_Invoices[Vendor],B51,AP_Invoices[Status],"Overdue")+COUNTIFS(AP_Invoices[Vendor],B51,AP_Invoices[Status],"Blocked")+COUNTIFS(AP_Invoices[Vendor],B51,AP_Invoices[Status],"In Review")+COUNTIFS(AP_Invoices[Vendor],B51,AP_Invoices[Status],"Partially Paid",AP_Invoices[Days Past Due],">"&0) -> 5 | F51: =SUMIF(AP_Invoices[Vendor],B51,AP_Invoices[Disc Missed]) -> 0 | G51: =COUNTIFS(AP_Invoices[Vendor],B51,AP_Invoices[Blocked 30d],TRUE())+COUNTIFS(AP_Invoices[Vendor],B51,AP_Invoices[Status],"Voided")+COUNTIFS(AP_Invoices[Vendor],B51,AP_Invoices[In Review 15d],TRUE()) -> 0
... B54: Cleaning Solutions | C54: =SUMIF(AP_Invoices[Vendor],B54,AP_Invoices[Outstanding USD]) -> 827.88 | D54: =COUNTIF(AP_Invoices[Vendor],B54) -> 10 | E54: =COUNTIFS(AP_Invoices[Vendor],B54,AP_Invoices[Status],"Overdue")+COUNTIFS(AP_Invoices[Vendor],B54,AP_Invoices[Status],"Blocked")+COUNTIFS(AP_Invoices[Vendor],B54,AP_Invoices[Status],"In Review")+COUNTIFS(AP_Invoices[Vendor],B54,AP_Invoices[Status],"Partially Paid",AP_Invoices[Days Past Due],">"&0) -> 2 | F54: =SUMIF(AP_Invoices[Vendor],B54,AP_Invoices[Disc Missed]) -> 0 | G54: =COUNTIFS(AP_Invoices[Vendor],B54,AP_Invoices[Blocked 30d],TRUE())+COUNTIFS(AP_Invoices[Vendor],B54,AP_Invoices[Status],"Voided")+COUNTIFS(AP_Invoices[Vendor],B54,AP_Invoices[In Review 15d],TRUE()) -> 2
B56: ▸ ► EXCEPTIONS BREAKDOWN — source for Exceptions tab
B57: Exception Type | C57: Total Count | D57: US01 | E57: US02 | F57: MX01 | G57: US03
B58: Blocked 30d+ | C58: =COUNTIF(AP_Invoices[Blocked 30d],TRUE()) -> 7 | D58: =COUNTIFS(AP_Invoices[Blocked 30d],TRUE(),AP_Invoices[Company],"US01") -> 2 | E58: =COUNTIFS(AP_Invoices[Blocked 30d],TRUE(),AP_Invoices[Company],"US02") -> 4 | F58: =COUNTIFS(AP_Invoices[Blocked 30d],TRUE(),AP_Invoices[Company],"MX01") -> 1 | G58: =COUNTIFS(AP_Invoices[Blocked 30d],TRUE(),AP_Invoices[Company],"US03") -> 0
B59: In Review 15d+ | C59: =COUNTIF(AP_Invoices[In Review 15d],TRUE()) -> 4 | D59: =COUNTIFS(AP_Invoices[In Review 15d],TRUE(),AP_Invoices[Company],"US01") -> 2 | E59: =COUNTIFS(AP_Invoices[In Review 15d],TRUE(),AP_Invoices[Company],"US02") -> 2 | F59: =COUNTIFS(AP_Invoices[In Review 15d],TRUE(),AP_Invoices[Company],"MX01") -> 0 | G59: =COUNTIFS(AP_Invoices[In Review 15d],TRUE(),AP_Invoices[Company],"US03") -> 0
B60: Voided | C60: =COUNTIF(AP_Invoices[Status],"Voided") -> 3 | D60: =COUNTIFS(AP_Invoices[Status],"Voided",AP_Invoices[Company],"US01") -> 0 | E60: =COUNTIFS(AP_Invoices[Status],"Voided",AP_Invoices[Company],"US02") -> 2 | F60: =COUNTIFS(AP_Invoices[Status],"Voided",AP_Invoices[Company],"MX01") -> 1 | G60: =COUNTIFS(AP_Invoices[Status],"Voided",AP_Invoices[Company],"US03") -> 0

Sheet Vendor Analysis
B1: Vendor Analysis
B3: Outstanding balance, overdue exposure, and discount performance by vendor — sorted by outstanding balance (highest first)
B4: Vendor | C4: Outstanding USD | D4: Invoice Count | E4: Overdue Count | F4: Disc Missed USD | G4: Exceptions | H4: Risk Signal
B5: ='Summary Tables'!B40 -> Fresh Beverages Inc | C5: ='Summary Tables'!C40 -> 13779.17 | D5: ='Summary Tables'!D40 -> 9 | E5: ='Summary Tables'!E40 -> 3 | F5: ='Summary Tables'!F40 -> 0 | G5: ='Summary Tables'!G40 -> 0 | H5: =IF(AND('Summary Tables'!G40>=5,'Summary Tables'!F40>0),"⚠ High — Exceptions + Missed Discount",IF('Summary Tables'!G40>=5,"⚠ High — Multiple Exceptions",IF('Summary Tables'!F40>50,"⚠ Review — Missed Discount",IF('Summary Tables'!C40>10000,"► Monitor — High Balance","✓ Normal")))) -> ► Monitor — High Balance
B6: ='Summary Tables'!B41 -> Continental Freight | C6: ='Summary Tables'!C41 -> 11030.14 | D6: ='Summary Tables'!D41 -> 9 | E6: ='Summary Tables'!E41 -> 4 | F6: ='Summary Tables'!F41 -> 451.08 | G6: ='Summary Tables'!G41 -> 1 | H6: =IF(AND('Summary Tables'!G41>=5,'Summary Tables'!F41>0),"⚠ High — Exceptions + Missed Discount",IF('Summary Tables'!G41>=5,"⚠ High — Multiple Exceptions",IF('Summary Tables'!F41>50,"⚠ Review — Missed Discount",IF('Summary Tables'!C41>10000,"► Monitor — High Balance","✓ Normal")))) -> ⚠ Review — Missed Discount
B7: ='Summary Tables'!B42 -> IT Services Group | C7: ='Summary Tables'!C42 -> 8700.57 | D7: ='Summary Tables'!D42 -> 9 | E7: ='Summary Tables'!E42 -> 4 | F7: ='Summary Tables'!F42 -> 0 | G7: ='Summary Tables'!G42 -> 1 | H7: =IF(AND('Summary Tables'!G42>=5,'Summary Tables'!F42>0),"⚠ High — Exceptions + Missed Discount",IF('Summary Tables'!G42>=5,"⚠ High — Multiple Exceptions",IF('Summary Tables'!F42>50,"⚠ Review — Missed Discount",IF('Summary Tables'!C42>10000,"► Monitor — High Balance","✓ Normal")))) -> ✓ Normal
B8: ='Summary Tables'!B43 -> Vendor One Foods | C8: ='Summary Tables'!C43 -> 7208.24 | D8: ='Summary Tables'!D43 -> 9 | E8: ='Summary Tables'!E43 -> 2 | F8: ='Summary Tables'!F43 -> 0 | G8: ='Summary Tables'!G43 -> 0 | H8: =IF(AND('Summary Tables'!G43>=5,'Summary Tables'!F43>0),"⚠ High — Exceptions + Missed Discount",IF('Summary Tables'!G43>=5,"⚠ High — Multiple Exceptions",IF('Summary Tables'!F43>50,"⚠ Review — Missed Discount",IF('Summary Tables'!C43>10000,"► Monitor — High Balance","✓ Normal")))) -> ✓ Normal
B9: ='Summary Tables'!B44 -> Logistics Partners | C9: ='Summary Tables'!C44 -> 6447.85 | D9: ='Summary Tables'!D44 -> 10 | E9: ='Summary Tables'!E44 -> 2 | F9: ='Summary Tables'!F44 -> 0 | G9: ='Summary Tables'!G44 -> 2 | H9: =IF(AND('Summary Tables'!G44>=5,'Summary Tables'!F44>0),"⚠ High — Exceptions + Missed Discount",IF('Summary Tables'!G44>=5,"⚠ High — Multiple Exceptions",IF('Summary Tables'!F44>50,"⚠ Review — Missed Discount",IF('Summary Tables'!C44>10000,"► Monitor — High Balance","✓ Normal")))) -> ✓ Normal
B10: ='Summary Tables'!B45 -> EuroFreight GmbH | C10: ='Summary Tables'!C45 -> 5696.25 | D10: ='Summary Tables'!D45 -> 6 | E10: ='Summary Tables'!E45 -> 2 | F10: ='Summary Tables'!F45 -> 0 | G10: ='Summary Tables'!G45 -> 0 | H10: =IF(AND('Summary Tables'!G45>=5,'Summary Tables'!F45>0),"⚠ High — Exceptions + Missed Discount",IF('Summary Tables'!G45>=5,"⚠ High — Multiple Exceptions",IF('Summary Tables'!F45>50,"⚠ Review — Missed Discount",IF('Summary Tables'!C45>10000,"► Monitor — High Balance","✓ Normal")))) -> ✓ Normal
B11: ='Summary Tables'!B46 -> Metro Packaging | C11: ='Summary Tables'!C46 -> 4829.39 | D11: ='Summary Tables'!D46 -> 8 | E11: ='Summary Tables'!E46 -> 4 | F11: ='Summary Tables'!F46 -> 100.9 | G11: ='Summary Tables'!G46 -> 1 | H11: =IF(AND('Summary Tables'!G46>=5,'Summary Tables'!F46>0),"⚠ High — Exceptions + Missed Discount",IF('Summary Tables'!G46>=5,"⚠ High — Multiple Exceptions",IF('Summary Tables'!F46>50,"⚠ Review — Missed Discount",IF('Summary Tables'!C46>10000,"► Monitor — High Balance","✓ Normal")))) -> ⚠ Review — Missed Discount
B12: ='Summary Tables'!B47 -> Northside Transport | C12: ='Summary Tables'!C47 -> 3607.89 | D12: ='Summary Tables'!D47 -> 9 | E12: ='Summary Tables'!E47 -> 1 | F12: ='Summary Tables'!F47 -> 0 | G12: ='Summary Tables'!G47 -> 0 | H12: =IF(AND('Summary Tables'!G47>=5,'Summary Tables'!F47>0),"⚠ High — Exceptions + Missed Discount",IF('Summary Tables'!G47>=5,"⚠ High — Multiple Exceptions",IF('Summary Tables'!F47>50,"⚠ Review — Missed Discount",IF('Summary Tables'!C47>10000,"► Monitor — High Balance","✓ Normal")))) -> ✓ Normal
B13: ='Summary Tables'!B48 -> City Utilities | C13: ='Summary Tables'!C48 -> 3052.83 | D13: ='Summary Tables'!D48 -> 10 | E13: ='Summary Tables'!E48 -> 5 | F13: ='Summary Tables'!F48 -> 0 | G13: ='Summary Tables'!G48 -> 1 | H13: =IF(AND('Summary Tables'!G48>=5,'Summary Tables'!F48>0),"⚠ High — Exceptions + Missed Discount",IF('Summary Tables'!G48>=5,"⚠ High — Multiple Exceptions",IF('Summary Tables'!F48>50,"⚠ Review — Missed Discount",IF('Summary Tables'!C48>10000,"► Monitor — High Balance","✓ Normal")))) -> ✓ Normal
B14: ='Summary Tables'!B49 -> Suministros MX | C14: ='Summary Tables'!C49 -> 2740.86 | D14: ='Summary Tables'!D49 -> 6 | E14: ='Summary Tables'!E49 -> 3 | F14: ='Summary Tables'!F49 -> 0 | G14: ='Summary Tables'!G49 -> 2 | H14: =IF(AND('Summary Tables'!G49>=5,'Summary Tables'!F49>0),"⚠ High — Exceptions + Missed Discount",IF('Summary Tables'!G49>=5,"⚠ High — Multiple Exceptions",IF('Summary Tables'!F49>50,"⚠ Review — Missed Discount",IF('Summary Tables'!C49>10000,"► Monitor — High Balance","✓ Normal")))) -> ✓ Normal
B15: ='Summary Tables'!B50 -> Packaging World | C15: ='Summary Tables'!C50 -> 2493.11 | D15: ='Summary Tables'!D50 -> 10 | E15: ='Summary Tables'!E50 -> 3 | F15: ='Summary Tables'!F50 -> 0 | G15: ='Summary Tables'!G50 -> 2 | H15: =IF(AND('Summary Tables'!G50>=5,'Summary Tables'!F50>0),"⚠ High — Exceptions + Missed Discount",IF('Summary Tables'!G50>=5,"⚠ High — Multiple Exceptions",IF('Summary Tables'!F50>50,"⚠ Review — Missed Discount",IF('Summary Tables'!C50>10000,"► Monitor — High Balance","✓ Normal")))) -> ✓ Normal
B16: ='Summary Tables'!B51 -> Office Supply Co | C16: ='Summary Tables'!C51 -> 2483.09 | D16: ='Summary Tables'!D51 -> 10 | E16: ='Summary Tables'!E51 -> 5 | F16: ='Summary Tables'!F51 -> 0 | G16: ='Summary Tables'!G51 -> 0 | H16: =IF(AND('Summary Tables'!G51>=5,'Summary Tables'!F51>0),"⚠ High — Exceptions + Missed Discount",IF('Summary Tables'!G51>=5,"⚠ High — Multiple Exceptions",IF('Summary Tables'!F51>50,"⚠ Review — Missed Discount",IF('Summary Tables'!C51>10000,"► Monitor — High Balance","✓ Normal")))) -> ✓ Normal
... B19: ='Summary Tables'!B54 -> Cleaning Solutions | C19: ='Summary Tables'!C54 -> 827.88 | D19: ='Summary Tables'!D54 -> 10 | E19: ='Summary Tables'!E54 -> 2 | F19: ='Summary Tables'!F54 -> 0 | G19: ='Summary Tables'!G54 -> 2 | H19: =IF(AND('Summary Tables'!G54>=5,'Summary Tables'!F54>0),"⚠ High — Exceptions + Missed Discount",IF('Summary Tables'!G54>=5,"⚠ High — Multiple Exceptions",IF('Summary Tables'!F54>50,"⚠ Review — Missed Discount",IF('Summary Tables'!C54>10000,"► Monitor — High Balance","✓ Normal")))) -> ✓ Normal

Sheet Formulas & Calculations
B1: Dashboard Formulas & Calculation Reference
B3: KPI / Metric | C3: Excel Formula (in Summary Tables) | D3: Source Column(s) | E3: Result
B4: KPI METRICS
B5: Total Outstanding (USD) | C5: =SUM(AP_Invoices[Outstanding USD]) | D5: outstanding_amount_usd = max(invoice_amount_usd − amount_paid_usd, 0) where both amounts are pre-converted to USD via fx_rate_used | E5: See Summary Tables D5
B6: On-Time Payment Rate | C6: =(COUNTIFS(AP_Invoices[Late Payment],FALSE(),AP_Invoices[Status],"Paid") +COUNTIFS(AP_Invoices[Late Payment],FALSE(),AP_Invoices[Status],"Partially Paid")) /(COUNTIF(AP_Invoices[Status],"Paid") +COUNTIF(AP_Invoices[Status],"Partially Paid")) | D6: late_payment_flag status | E6: See Summary Tables D7
B7: Discount Capture Rate | C7: =SUM(AP_Invoices[Disc Captured]) /(SUM(AP_Invoices[Disc Captured])+SUM(AP_Invoices[Disc Missed])) | D7: captured_discount_value missed_discount_value | E7: See Summary Tables D8
B8: Critical Exceptions | C8: =COUNTIF(AP_Invoices[Blocked 30d],TRUE()) +COUNTIF(AP_Invoices[Status],"Voided") +COUNTIF(AP_Invoices[In Review 15d],TRUE()) | D8: blocked_over_30_days status in_review_over_15_days | E8: See Summary Tables D9
B9: CHART DATA
B10: Aging — Outstanding by Bucket | C10: =SUMIF(AP_Invoices[Aging Bucket],<bucket>,AP_Invoices[Outstanding USD]) one formula per bucket row in Summary Tables C14:C18 | D10: aging_bucket outstanding_amount_usd | E10: Summary Tables C14:C18
B11: Discount — Captured by Month | C11: =SUMIF(AP_Invoices[Month],<month>,AP_Invoices[Disc Captured]) one formula per month row in summary tables C22:C27 | D11: posting_month_label captured_discount_value | E11: Summary Tables C22:C27
B12: Discount — Missed by Month | C12: =SUMIF(AP_Invoices[Month],<month>,AP_Invoices[Disc Missed]) one formula per month row in summary tables D22:D27 | D12: posting_month_label missed_discount_value | E12: Summary Tables D22:D27
B13: DERIVED FLAGS (computed in Python — Stage 2)
B14: late_payment_flag | C14: TRUE when status = "Paid", payment_date is not null, due_date is not null, and payment_date > due_date. Comparison is against due_date — not payment terms parsing. | D14: status payment_date due_date | E14: Boolean
B15: blocked_over_30_days | C15: TRUE when status = "Blocked" and (snapshot_date − posting_date) > 30 days. Status is used rather than raw payment_block presence because it more accurately reflects operational state. | D15: status posting_date snapshot_date | E15: Boolean
B16: in_review_over_15_days | C16: status = 'In Review' AND days_open_as_of_snapshot > 15 | D16: status days_open_as_of_snapshot | E16: Boolean
B17: aging_bucket | C17: Current = not overdue as of the snapshot date 0-30 Days = overdue; days_past_due between 1 and 30 31-60 Days = overdue; days_past_due between 31 and 60 61-90 Days = overdue; days_past_due between 61 and 90 90+ Days = overdue; days_past_due greater than 90 | D17: days_past_due snapshot_date due_date | E17: Categorical
B18: outstanding_amount_usd | C18: invoice_amount_usd = invoice_amount × fx_rate_used amount_paid_usd = amount_paid × fx_rate_used outstanding_amount_usd = max(invoice_amount_usd − amount_paid_usd, 0) Rounded to 2 decimal places. | D18: invoice_amount amount_paid fx_rate_used | E18: Numeric USD
B19: is_overdue | C19: OR([@Status]="Overdue", [@Status]="Blocked", [@Status]="In Review", AND([@Status]="Partially Paid", [@[Days Past Due]]>0)) | D19: Status Days Past Due | E19: Boolean — used in Vendor Overdue Count formulas

Sheet Project Pipeline
B1: Project Pipeline — End-to-End Data Flow
B3: Stage | C3: Description | D3: File / Reference
B4: STAGE 1 | C4: Data Source — Raw AP Records
C5: Raw AP invoice records simulating an ERP export (SAP / Oracle structure). 130 invoices · 57 columns · Jan – Jun 2025 4 company codes (US01, US02, US03, MX01) · 15 vendors · 3 currencies (USD, EUR, MXN) Includes invoice dates, due dates, payment dates, amounts, statuses, PO references. | D5: ap_invoices_raw.csv
B7: STAGE 2 | C7: Python / Pandas — Data Transformation
C8: Python script ingests the raw CSV and derives all calculated columns: • days_to_pay = payment_date − posting_date • outstanding_amount_usd = invoice_amount × fx_rate − amount_paid • aging_bucket from days_past_due thresholds (Current / 0-30 / 31-60 / 61-90 / 90+) • late_payment_flag, blocked_over_30_days, in_review_over_15_days • discount_captured_calc, captured_discount_value, missed_discount_value • urgency_level and issue_type classification Outputs the clean row-level CSV loaded into the Data sheet of this workbook. | D8: ap_pipeline.py → GitHub repo
B10: STAGE 3 | C10: SQL — Business Questions on Clean Data
C11: SQL queries written against the Stage 2 cleaned dataset to answer AP business questions: • Which vendors carry the highest outstanding balances and for how long? • What is the on-time payment rate by company code and fiscal period? • How much early-payment discount was lost and which vendors caused it? • Which invoices are blocked, voided, or in review beyond SLA thresholds? SQL runs on clean data — it answers questions, not transform raw data. Results cross-validate the KPI numbers in this dashboard. | D11: ap_analysis.sql → GitHub repo
B13: STAGE 4 | C13: Excel Dashboard — This Workbook
C14: Built with Python (openpyxl) to load the Data sheet, then Excel formulas do the work: • SUMIF / COUNTIF / COUNTIFS in Summary Tables aggregate all metrics • KPI cards on Dashboard reference Summary Tables via cell formulas • Charts are built from Summary Tables ranges — no hardcoded values • All formula logic documented in the Formulas & Calculations tab | D14: AP_Management_Dashboard.xlsx
